extended_algo_vector/__init__.py
extended_algo_vector/engine/OrderDetails.py
extended_algo_vector/engine/VectorStrategy.py
extended_algo_vector/engine/create_audit_file.py
extended_algo_vector/engine/create_consolidated_stats.py
extended_algo_vector/engine/create_limit_entries.py
extended_algo_vector/engine/create_stop_entries.py
extended_algo_vector/market/MarketData.py
extended_algo_vector/market/__init__.py
extended_algo_vector/market/qualify_contracts.py
extended_algo_vector/market/bars/SecondsDollarBars.py
extended_algo_vector/market/bars/SecondsVolumeBars.py
extended_algo_vector/market/bars/TickBars.py
extended_algo_vector/market/bars/TickDollarBars.py
extended_algo_vector/market/bars/TickRangeBars.py
extended_algo_vector/market/bars/TickVolumeBars.py
extended_algo_vector/market/bars/Ticks.py
extended_algo_vector/market/bars/TimeBars.py
extended_algo_vector/market/bars/__init__.py
extended_algo_vector/market/events/EconomicCalendar.py
extended_algo_vector/market/utils/common.py
extended_algo_vector/market/utils/resample_market_data.py
extended_algo_vector/market/utils/use_cached_market_data.py
extended_algo_vector/report/CalculatePnLStats.py
extended_algo_vector/report/ConstructPortfolioOfStrategies.py
extended_algo_vector/report/calculate/Features.py
extended_algo_vector/report/calculate/MaeMfe.py
extended_algo_vector/report/calculate/Stats.py
extended_algo_vector/report/utils/read_strategy_metadata.py
extended_algo_vector-0.0.1.4.dist-info/METADATA
extended_algo_vector-0.0.1.4.dist-info/WHEEL
extended_algo_vector-0.0.1.4.dist-info/top_level.txt
extended_algo_vector-0.0.1.4.dist-info/RECORD
